LICENSE
MANIFEST.in
README.rst
requirements.txt
setup.py
babbler/__init__.py
babbler/bot.py
babbler/feed.py
babbler/options.py
babbler/persistence.py
babbler/responder.py
babbler/tagging.py
babbler.egg-info/PKG-INFO
babbler.egg-info/SOURCES.txt
babbler.egg-info/dependency_links.txt
babbler.egg-info/entry_points.txt
babbler.egg-info/requires.txt
babbler.egg-info/top_level.txt
babbler/data/dictionary.txt
babbler/data/eliza.yml
babbler/data/options.yml
babbler/data/stopwords.txt