Metadata-Version: 1.0
Name: babbler
Version: 0.3.4
Summary: A Twitter bot that polls an RSS feed and posts its entries as tweets, with auto-generated hashtags. For extra mischief, replies to the bot are responded to using a basic Eliza implementation.  After installing, the 'babbler' command will be available which you can use to run the bot. Data will be stored in the current directory.
Home-page: http://github.com/stephenmcd/babbler/
Author: Stephen McDonald
Author-email: stephen.mc@gmail.com
License: BSD
Platform: UNKNOWN
Classifier: Development Status :: 4 - Beta
Classifier: Environment :: Console
Classifier: Intended Audience :: Developers
Classifier: Intended Audience :: End Users/Desktop
Classifier: License :: OSI Approved :: BSD License
Classifier: Operating System :: POSIX
Classifier: Programming Language :: Python
Classifier: Topic :: Communications
Classifier: Topic :: Text Processing
